[
    {
        "title": "Integración",
        "featureList": [
            "Estudio y diseño del proyecto",
            "Prescripción técnica",
            "Suministro de los equipos",
            "Instalación y configuración",
            "Puesta en marcha",
            "Garantía sujeta a mantenimiento"
        ],
        "claim": "Soluciones audiovisuales e integradas de imagen y sonido",
        "url": "integracion",
        "featureImage": {
            "name": "Imágen destacada de los servicios de integración de Backup AV",
            "url": "/servicios-integracion-bg.jpg",
            "width": 2000,
            "height": 1381
        }
    },
    {
        "title": "Mantenimiento",
        "featureList": [
            "Mantenimiento correctivo",
            "Mantenimiento preventivo",
            "SAT (Reparaciones)"
        ],
        "claim": "Soluciones audiovisuales e integradas de imagen y sonido",
        "url": "mantenimiento",
        "featureImage": {
            "name": "Imágen destacada de los servicios de mantenimiento de Backup AV",
            "url": "/servicios-mantenimiento-bg.jpg",
            "width": 2000,
            "height": 957
        }
    },
    {
        "title": "Eventos",
        "featureList": [
            "Estudio y diseño del proyecto",
            "Propuesta técnica",
            "Suministro de los equipos audiovisuales con o sin técnico"
        ],
        "claim": "Desarrollo, ejecución e infraestructura técnica en todo tipo de eventos",
        "url": "eventos",
        "featureImage": {
            "name": "Imágen destacada de los servicios de eventos de Backup AV",
            "url": "/servicios-eventos-bg.jpg",
            "width": 2000,
            "height": 1333
        }
    }
]
