[
    {
        "title": "Integración",
        "featureList": [
            "Estudio y diseño del proyecto",
            "Prescripción técnica",
            "Suministro de los equipos",
            "Instalación y configuración",
            "Puesta en marcha",
            "Garantía sujeta a mantenimiento"
        ],
        "claim": "Soluciones audiovisuales e integradas de imagen y sonido",
        "url": "integracion"
    },
    {
        "title": "Mantenimiento",
        "featureList": [
            "Mantenimiento correctivo",
            "Mantenimiento preventivo",
            "SAT (Reparaciones)"
        ],
        "claim": "Soluciones audiovisuales e integradas de imagen y sonido",
        "url": "mantenimiento"
    },
    {
        "title": "Eventos",
        "featureList": [
            "Estudio y diseño del proyecto",
            "Propuesta técnica",
            "Suministro de los equipos audiovisuales con o sin técnico"
        ],
        "claim": "Desarrollo, ejecución e infraestructura técnica en todo tipo de eventos",
        "url": "eventos"
    }
]
